LICENSE
MANIFEST.in
README.md
requirements.txt
setup.py
versiontools.py
pyPRISM/__init__.py
pyPRISM/version.py
pyPRISM.egg-info/PKG-INFO
pyPRISM.egg-info/SOURCES.txt
pyPRISM.egg-info/dependency_links.txt
pyPRISM.egg-info/requires.txt
pyPRISM.egg-info/top_level.txt
pyPRISM/calculate/__init__.py
pyPRISM/calculate/chi.py
pyPRISM/calculate/pair_correlation.py
pyPRISM/calculate/pmf.py
pyPRISM/calculate/second_virial.py
pyPRISM/calculate/solvation_potential.py
pyPRISM/calculate/spinodal_condition.py
pyPRISM/calculate/structure_factor.py
pyPRISM/closure/AtomicClosure.py
pyPRISM/closure/Closure.py
pyPRISM/closure/HyperNettedChain.py
pyPRISM/closure/MartynovSarkisov.py
pyPRISM/closure/MeanSphericalApproximation.py
pyPRISM/closure/MolecularClosure.py
pyPRISM/closure/PercusYevick.py
pyPRISM/closure/ReferenceMolecularPercusYevick.py
pyPRISM/closure/__init__.py
pyPRISM/core/Density.py
pyPRISM/core/Diameter.py
pyPRISM/core/Domain.py
pyPRISM/core/IdentityMatrixArray.py
pyPRISM/core/MatrixArray.py
pyPRISM/core/PRISM.py
pyPRISM/core/PairTable.py
pyPRISM/core/Space.py
pyPRISM/core/System.py
pyPRISM/core/Table.py
pyPRISM/core/ValueTable.py
pyPRISM/core/__init__.py
pyPRISM/omega/DiscreteKoyama.py
pyPRISM/omega/FreelyJointedChain.py
pyPRISM/omega/FromArray.py
pyPRISM/omega/FromFile.py
pyPRISM/omega/Gaussian.py
pyPRISM/omega/GaussianRing.py
pyPRISM/omega/InterMolecular.py
pyPRISM/omega/NoIntra.py
pyPRISM/omega/NonOverlappingFreelyJointedChain.py
pyPRISM/omega/Omega.py
pyPRISM/omega/SingleSite.py
pyPRISM/omega/__init__.py
pyPRISM/potential/Exponential.py
pyPRISM/potential/HardCoreLennardJones.py
pyPRISM/potential/HardSphere.py
pyPRISM/potential/LennardJones.py
pyPRISM/potential/Potential.py
pyPRISM/potential/WeeksChandlerAndersen.py
pyPRISM/potential/__init__.py
pyPRISM/test/CalcPRISM_test.py
pyPRISM/test/Debyer_test.py
pyPRISM/test/Density_test.py
pyPRISM/test/Diameter_test.py
pyPRISM/test/Domain_test.py
pyPRISM/test/Exponential_test.py
pyPRISM/test/FreelyJointedChain_test.py
pyPRISM/test/FromArray_test.py
pyPRISM/test/FromFile_test.py
pyPRISM/test/GaussianRing_test.py
pyPRISM/test/Gaussian_test.py
