Metadata-Version: 2.1
Name: pyPRISM
Version: 1.0.4
Summary: A python tool for Polymer Reference Interaction Site Model (PRISM) calculations
Home-page: https://github.com/usnistgov/pyprism
Author: Tyler B. Martin
Author-email: tyler.martin@nist.gov
License: LICENSE
Project-URL: Bug Reports, https://github.com/usnistgov/pyprism/issues
Project-URL: Source, https://github.com/usnistgov/pyprism
Project-URL: Documentation, http://pyPRISM.readthedocs.io
Keywords: materials science polymer theory simulation X-ray neutron scattering liquid-state nanocomposite
Platform: UNKNOWN
Classifier: Development Status :: 4 - Beta
Classifier: Intended Audience :: Science/Research
Classifier: License :: Freely Distributable
Classifier: License :: Freeware
Classifier: License :: Public Domain
Classifier: Natural Language :: English
Classifier: Operating System :: MacOS
Classifier: Operating System :: Microsoft
Classifier: Operating System :: Unix
Classifier: Programming Language :: Python
Classifier: Programming Language :: Python :: 2
Classifier: Programming Language :: Python :: 2.7
Classifier: Programming Language :: Python :: 2 :: Only
Classifier: Programming Language :: Python :: 3
Classifier: Programming Language :: Python :: 3.5
Classifier: Programming Language :: Python :: 3.6
Classifier: Programming Language :: Python :: Implementation :: CPython
Classifier: Topic :: Scientific/Engineering
Classifier: Topic :: Scientific/Engineering :: Chemistry
Classifier: Topic :: Scientific/Engineering :: Physics
